enrich/__init__.py
enrich_api-1.1.1.dist-info/DESCRIPTION.rst
enrich_api-1.1.1.dist-info/METADATA
enrich_api-1.1.1.dist-info/RECORD
enrich_api-1.1.1.dist-info/WHEEL
enrich_api-1.1.1.dist-info/metadata.json
enrich_api-1.1.1.dist-info/top_level.txt
