Metadata-Version: 2.0
Name: enrich-api
Version: 1.1.1
Summary: Enrich API Python.
Home-page: https://github.com/enrich-data/enrich-api-python
Author: Valerian Saliou
Author-email: valerian@valeriansaliou.name
License: MIT - http://opensource.org/licenses/mit-license.php
Platform: UNKNOWN
Classifier: Environment :: Web Environment
Classifier: Intended Audience :: Developers
Classifier: Natural Language :: English
Classifier: Programming Language :: Python
